upandas/__init__.py
upandas/testing.py
upandas/upandas.py
upandas-0.2.0.dist-info/LICENSE
upandas-0.2.0.dist-info/WHEEL
upandas-0.2.0.dist-info/METADATA
upandas-0.2.0.dist-info/RECORD
