Metadata-Version: 2.1
Name: upandas
Version: 0.2.0
Summary: Handle uncertainties within pandas dataframes and series
Home-page: https://bitbucket.org/lincolndturner/upandas
License: BSD-2-Clause
Keywords: pandas,uncertainties,uarray,dataframe,errors
Author: Lincoln Turner
Author-email: lincoln.turner@monash.edu
Requires-Python: >=3.7,<4.0
Classifier: License :: OSI Approved :: BSD License
Classifier: Programming Language :: Python :: 3
Classifier: Programming Language :: Python :: 3.7
Requires-Dist: pandas (>=0.24,<0.25)
Requires-Dist: uncertainties (>=3.1,<4.0)
Project-URL: Repository, https://bitbucket.org/lincolndturner/upandas
